README.rst
movie_searcher.py
setup.py
movie_searcher.egg-info/PKG-INFO
movie_searcher.egg-info/SOURCES.txt
movie_searcher.egg-info/dependency_links.txt
movie_searcher.egg-info/requires.txt
movie_searcher.egg-info/top_level.txt